README.txt
setup.py
inqbus/__init__.py
inqbus.folderlistings.egg-info/PKG-INFO
inqbus.folderlistings.egg-info/SOURCES.txt
inqbus.folderlistings.egg-info/dependency_links.txt
inqbus.folderlistings.egg-info/entry_points.txt
inqbus.folderlistings.egg-info/namespace_packages.txt
inqbus.folderlistings.egg-info/not-zip-safe
inqbus.folderlistings.egg-info/requires.txt
inqbus.folderlistings.egg-info/top_level.txt
inqbus/folderlistings/__init__.py
inqbus/folderlistings/browser/__init__.py
inqbus/folderlistings/browser/inqbus_folderlistings.py
inqbus/folderlistings/tests/__init__.py
inqbus/folderlistings/tests/base.py
inqbus/folderlistings/tests/test_functionalities.py